[
  {
    "id": 1,
    "name": "TaskMaster Pro",
    "category": "Productivity",
    "price": "4.99",
    "priceLabel": "$4.99",
    "description": "The ultimate task management app that helps you organize your work and life.",
    "rating": 4.8,
    "reviews": 2300,
    "imageUrl": "https://cdn-icons-png.flaticon.com/512/2387/2387635.png",
    "isPaid": true,
    "features": [
      "Create and organize tasks with categories",
      "Set reminders and deadlines",
      "Track your productivity with analytics",
      "Sync across all your devices",
      "Collaborate with team members",
      "Dark mode support"
    ],
    "screenshots": [
      "https://images.unsplash.com/photo-1607252650355-f7fd0460ccdb?ixlib=rb-4.0.3&ixid=MnwxMjA3fDB8MHxwaG90by1wYWdlfHx8fGVufDB8fHx8&auto=format&fit=crop&w=800&h=450",
      "https://images.unsplash.com/photo-1551288049-bebda4e38f71?ixlib=rb-4.0.3&ixid=MnwxMjA3fDB8MHxwaG90by1wYWdlfHx8fGVufDB8fHx8&auto=format&fit=crop&w=800&h=450"
    ],
    "developer": "Polifilo Software Inc.",
    "releaseDate": "June 15, 2023",
    "version": "2.1.3",
    "size": "4.2 MB",
    "website": "https://example.com/taskmaster",
    "apkFile": "/apk/sample-app.apk"
  },
  {
    "id": 2,
    "name": "FitTrack",
    "category": "Health & Fitness",
    "price": null,
    "priceLabel": "Free",
    "description": "Track your workouts, monitor progress, and achieve your fitness goals.",
    "rating": 4.6,
    "reviews": 1500,
    "imageUrl": "https://cdn-icons-png.flaticon.com/512/2936/2936886.png",
    "isPaid": false,
    "features": [
      "Track over 100 different exercises",
      "Create custom workout routines",
      "Monitor calories burned",
      "Connect with fitness trackers",
      "Progress charts and analytics",
      "Community challenges"
    ],
    "screenshots": [
      "https://cdn.pixabay.com/photo/2020/04/02/22/09/fitness-4996855_1280.jpg",
      "https://cdn.pixabay.com/photo/2017/01/09/11/30/dumbbell-1966247_1280.jpg"
    ],
    "developer": "HealthTech Solutions",
    "releaseDate": "March 3, 2023",
    "version": "3.0.5",
    "size": "8.7 MB",
    "website": "https://example.com/fittrack",
    "apkFile": "/apk/game-sample.apk"
  },
  {
    "id": 3,
    "name": "StreamHub",
    "category": "Entertainment",
    "price": "3.99",
    "priceLabel": "$3.99",
    "description": "Stream your favorite content with personalized recommendations.",
    "rating": 4.7,
    "reviews": 3200,
    "imageUrl": "https://cdn-icons-png.flaticon.com/512/2463/2463510.png",
    "isPaid": true,
    "features": [
      "Access to thousands of movies and shows",
      "Create personalized playlists",
      "Download content for offline viewing",
      "Family sharing across 5 accounts",
      "4K Ultra HD streaming",
      "Ad-free experience"
    ],
    "screenshots": [
      "https://images.unsplash.com/photo-1493711662062-fa541adb3fc8?ixlib=rb-4.0.3&ixid=MnwxMjA3fDB8MHxwaG90by1wYWdlfHx8fGVufDB8fHx8&auto=format&fit=crop&w=800&h=450",
      "https://images.unsplash.com/photo-1522869635100-9f4c5e86aa37?ixlib=rb-4.0.3&ixid=MnwxMjA3fDB8MHxwaG90by1wYWdlfHx8fGVufDB8fHx8&auto=format&fit=crop&w=800&h=450"
    ],
    "developer": "MediaStream Technologies",
    "releaseDate": "January 12, 2023",
    "version": "4.2.1",
    "size": "85 MB",
    "website": "https://example.com/streamhub",
    "apkFile": "/apk/sample-app.apk"
  },
  {
    "id": 4,
    "name": "MindfulMe",
    "category": "Lifestyle",
    "price": null,
    "priceLabel": "Free",
    "description": "Guided meditation and mindfulness exercises for daily peace.",
    "rating": 4.9,
    "reviews": 4700,
    "imageUrl": "https://cdn-icons-png.flaticon.com/512/3075/3075928.png",
    "isPaid": false,
    "features": [
      "Over 200 guided meditations",
      "Sleep stories and calming sounds",
      "Breathing exercises",
      "Mood tracking",
      "Daily mindfulness reminders",
      "Progress tracking"
    ],
    "screenshots": [
      "https://images.unsplash.com/photo-1518640467707-6811f4a6ab73?ixlib=rb-4.0.3&ixid=MnwxMjA3fDB8MHxwaG90by1wYWdlfHx8fGVufDB8fHx8&auto=format&fit=crop&w=800&h=450",
      "https://images.unsplash.com/photo-1506126613408-eca07ce68773?ixlib=rb-4.0.3&ixid=MnwxMjA3fDB8MHxwaG90by1wYWdlfHx8fGVufDB8fHx8&auto=format&fit=crop&w=800&h=450"
    ],
    "developer": "Zen Digital LLC",
    "releaseDate": "April 22, 2023",
    "version": "2.4.0",
    "size": "32 MB",
    "website": "https://example.com/mindfulme",
    "apkFile": "/apk/game-sample.apk"
  },
  {
    "id": 5,
    "name": "NotePro",
    "category": "Productivity",
    "price": "2.99",
    "priceLabel": "$2.99",
    "description": "Smart note-taking app with organization features and cloud sync.",
    "rating": 4.5,
    "reviews": 2800,
    "imageUrl": "https://cdn-icons-png.flaticon.com/512/2665/2665632.png",
    "isPaid": true,
    "features": [
      "Create rich text notes with formatting",
      "Organize with tags and folders",
      "Cloud sync across devices",
      "Voice-to-text transcription",
      "Embed images and documents",
      "Powerful search functionality"
    ],
    "screenshots": [
      "https://images.unsplash.com/photo-1512758017271-d7b84c2113f1?ixlib=rb-4.0.3&ixid=MnwxMjA3fDB8MHxwaG90by1wYWdlfHx8fGVufDB8fHx8&auto=format&fit=crop&w=800&h=450",
      "https://images.unsplash.com/photo-1494178270175-e96de6971df1?ixlib=rb-4.0.3&ixid=MnwxMjA3fDB8MHxwaG90by1wYWdlfHx8fGVufDB8fHx8&auto=format&fit=crop&w=800&h=450"
    ],
    "developer": "Productivity Works",
    "releaseDate": "February 8, 2023",
    "version": "3.1.2",
    "size": "28 MB",
    "website": "https://example.com/notepro",
    "apkFile": "/apk/sample-app.apk"
  },
  {
    "id": 6,
    "name": "DreamTrack",
    "category": "Health & Fitness",
    "price": "1.99",
    "priceLabel": "$1.99",
    "description": "Sleep tracker with insights to improve your sleep quality and habits.",
    "rating": 4.4,
    "reviews": 1900,
    "imageUrl": "https://cdn-icons-png.flaticon.com/512/4497/4497509.png",
    "isPaid": true,
    "features": [
      "Track sleep patterns and quality",
      "Smart alarm for optimal wake times",
      "Soothing sleep sounds library",
      "Weekly sleep reports and trends",
      "Sleep goal setting",
      "Integration with health apps"
    ],
    "screenshots": [
      "https://cdn.pixabay.com/photo/2021/11/11/14/19/woman-6786626_1280.jpg",
      "https://cdn.pixabay.com/photo/2019/11/10/17/36/moon-4616333_1280.jpg"
    ],
    "developer": "SleepWell Technologies",
    "releaseDate": "May 17, 2023",
    "version": "1.8.4",
    "size": "38 MB",
    "website": "https://example.com/dreamtrack",
    "apkFile": "/apk/game-sample.apk"
  },
  {
    "id": 7,
    "name": "WeatherNow",
    "category": "Weather",
    "price": null,
    "priceLabel": "Free",
    "description": "Accurate local weather forecasts, radar maps, and severe weather alerts.",
    "rating": 4.7,
    "reviews": 8500,
    "imageUrl": "https://cdn-icons-png.flaticon.com/512/1779/1779940.png",
    "isPaid": false,
    "features": [
      "Hourly and 10-day forecasts",
      "Real-time rain and snow alerts",
      "Interactive radar maps",
      "Air quality index",
      "UV index tracking",
      "Widget support"
    ],
    "screenshots": [],
    "developer": "Weather Systems Inc.",
    "releaseDate": "January 5, 2023",
    "version": "5.2.1",
    "size": "25 MB",
    "website": "https://example.com/weathernow",
    "apkFile": "/apk/sample-app.apk"
  },
  {
    "id": 8,
    "name": "PhotoEdit Pro",
    "category": "Photography",
    "price": "4.99",
    "priceLabel": "$4.99",
    "description": "Professional photo editing tools with filters, effects, and adjustments.",
    "rating": 4.6,
    "reviews": 5200,
    "imageUrl": "https://cdn-icons-png.flaticon.com/512/3342/3342137.png",
    "isPaid": true,
    "features": [
      "Advanced photo editing tools",
      "100+ filters and effects",
      "Layer support",
      "Smart object removal",
      "HDR enhancement",
      "Raw file support"
    ],
    "screenshots": [],
    "developer": "Creative Apps Studio",
    "releaseDate": "March 15, 2023",
    "version": "2.8.0",
    "size": "76 MB",
    "website": "https://example.com/photoeditpro",
    "apkFile": "/apk/sample-app.apk"
  },
  {
    "id": 9,
    "name": "RecipeBook",
    "category": "Food & Drink",
    "price": null,
    "priceLabel": "Free",
    "description": "Collection of recipes with step-by-step instructions and meal planning.",
    "rating": 4.3,
    "reviews": 3800,
    "imageUrl": "https://cdn-icons-png.flaticon.com/512/1046/1046747.png",
    "isPaid": false,
    "features": [
      "1000+ recipes across cuisines",
      "Shopping list generator",
      "Meal planning calendar",
      "Nutritional information",
      "Dietary filters (vegan, gluten-free, etc.)",
      "Recipe saving and sharing"
    ],
    "screenshots": [],
    "developer": "Culinary Software Solutions",
    "releaseDate": "February 12, 2023",
    "version": "3.4.2",
    "size": "42 MB",
    "website": "https://example.com/recipebook",
    "apkFile": "/apk/game-sample.apk"
  },
  {
    "id": 10,
    "name": "BudgetBuddy",
    "category": "Finance",
    "price": "2.99",
    "priceLabel": "$2.99",
    "description": "Personal finance manager to track expenses, budgets, and savings goals.",
    "rating": 4.5,
    "reviews": 6200,
    "imageUrl": "https://cdn-icons-png.flaticon.com/512/2474/2474475.png",
    "isPaid": true,
    "features": [
      "Expense tracking and categorization",
      "Monthly budget planning",
      "Bill payment reminders",
      "Savings goals tracking",
      "Financial reports and insights",
      "Bank account linking"
    ],
    "screenshots": [],
    "developer": "Financial Software Co.",
    "releaseDate": "April 8, 2023",
    "version": "4.1.0",
    "size": "35 MB",
    "website": "https://example.com/budgetbuddy",
    "apkFile": "/apk/sample-app.apk"
  },
  {
    "id": 11,
    "name": "LanguageMaster",
    "category": "Education",
    "price": "5.99",
    "priceLabel": "$5.99",
    "description": "Learn new languages with interactive lessons, vocabulary building, and pronunciation practice.",
    "rating": 4.8,
    "reviews": 7800,
    "imageUrl": "https://cdn-icons-png.flaticon.com/512/3898/3898082.png",
    "isPaid": true,
    "features": [
      "30+ languages available",
      "Interactive lessons and quizzes",
      "Speech recognition for pronunciation",
      "Offline mode",
      "Daily practice reminders",
      "Progress tracking"
    ],
    "screenshots": [],
    "developer": "Educational Technologies Inc.",
    "releaseDate": "January 20, 2023",
    "version": "5.3.2",
    "size": "84 MB",
    "website": "https://example.com/languagemaster",
    "apkFile": "/apk/game-sample.apk"
  },
  {
    "id": 12,
    "name": "WorldNews",
    "category": "News",
    "price": null,
    "priceLabel": "Free",
    "description": "Stay updated with the latest headlines, breaking news, and personalized news feed.",
    "rating": 4.2,
    "reviews": 9500,
    "imageUrl": "https://cdn-icons-png.flaticon.com/512/2965/2965879.png",
    "isPaid": false,
    "features": [
      "Breaking news alerts",
      "Personalized news feed",
      "Multiple news sources",
      "Offline reading",
      "Audio news playback",
      "Night reading mode"
    ],
    "screenshots": [],
    "developer": "Global Media Group",
    "releaseDate": "May 5, 2023",
    "version": "2.7.1",
    "size": "32 MB",
    "website": "https://example.com/worldnews",
    "apkFile": "/apk/sample-app.apk"
  },
  {
    "id": 13,
    "name": "SkyView Lite",
    "category": "Education",
    "price": null,
    "priceLabel": "Free",
    "description": "Explore the night sky with augmented reality star gazing and celestial object identification.",
    "rating": 4.7,
    "reviews": 12000,
    "imageUrl": "https://cdn-icons-png.flaticon.com/512/3049/3049490.png",
    "isPaid": false,
    "features": [
      "AR star mapping",
      "Planet, star, and constellation identification",
      "Night mode",
      "Satellite tracking",
      "Celestial event calendar",
      "Time machine function to view past/future skies"
    ],
    "screenshots": [],
    "developer": "Astronomy Apps LLC",
    "releaseDate": "February 28, 2023",
    "version": "3.5.0",
    "size": "55 MB",
    "website": "https://example.com/skyview",
    "apkFile": "/apk/game-sample.apk"
  },
  {
    "id": 14,
    "name": "Shopify",
    "category": "Shopping",
    "price": null,
    "priceLabel": "Free",
    "description": "Discover and buy trending products from thousands of brands.",
    "rating": 4.4,
    "reviews": 15000,
    "imageUrl": "https://cdn-icons-png.flaticon.com/512/732/732244.png",
    "isPaid": false,
    "features": [
      "Personalized product recommendations",
      "Easy checkout process",
      "Order tracking",
      "Wish list creation",
      "Deal alerts",
      "Multiple payment options"
    ],
    "screenshots": [],
    "developer": "Shopify Inc.",
    "releaseDate": "January 15, 2023",
    "version": "6.2.1",
    "size": "48 MB",
    "website": "https://example.com/shopify",
    "apkFile": "/apk/sample-app.apk"
  },
  {
    "id": 15,
    "name": "TravelPlanner",
    "category": "Travel",
    "price": "3.99",
    "priceLabel": "$3.99",
    "description": "Comprehensive travel planning app with itinerary building, booking, and travel guides.",
    "rating": 4.6,
    "reviews": 8300,
    "imageUrl": "https://cdn-icons-png.flaticon.com/512/201/201623.png",
    "isPaid": true,
    "features": [
      "Itinerary planning and management",
      "Hotel and flight booking",
      "Offline maps and guides",
      "Budget tracking",
      "Local recommendations",
      "Travel document storage"
    ],
    "screenshots": [],
    "developer": "Travel Technologies Ltd",
    "releaseDate": "March 22, 2023",
    "version": "4.0.3",
    "size": "72 MB",
    "website": "https://example.com/travelplanner",
    "apkFile": "/apk/game-sample.apk"
  },
  {
    "id": 16,
    "name": "ScanPro",
    "category": "Tools",
    "price": "1.99",
    "priceLabel": "$1.99",
    "description": "Document scanner with OCR, PDF creation, and document organization features.",
    "rating": 4.5,
    "reviews": 6700,
    "imageUrl": "https://cdn-icons-png.flaticon.com/512/1150/1150358.png",
    "isPaid": true,
    "features": [
      "Document scanning",
      "OCR text recognition",
      "PDF creation and editing",
      "Document organization",
      "Cloud storage integration",
      "Signature capture"
    ],
    "screenshots": [],
    "developer": "Productivity Tools Inc.",
    "releaseDate": "April 12, 2023",
    "version": "2.3.5",
    "size": "45 MB",
    "website": "https://example.com/scanpro",
    "apkFile": "/apk/sample-app.apk"
  },
  {
    "id": 17,
    "name": "Spotify",
    "category": "Music & Audio",
    "price": null,
    "priceLabel": "Free",
    "description": "Stream music, discover new songs, and create playlists with millions of tracks.",
    "rating": 4.8,
    "reviews": 25000,
    "imageUrl": "https://cdn-icons-png.flaticon.com/512/174/174872.png",
    "isPaid": false,
    "features": [
      "Millions of songs and podcasts",
      "Personalized playlists",
      "Offline listening",
      "Cross-device syncing",
      "High-quality audio",
      "Social sharing"
    ],
    "screenshots": [],
    "developer": "Spotify AB",
    "releaseDate": "January 8, 2023",
    "version": "8.7.0",
    "size": "52 MB",
    "website": "https://example.com/spotify",
    "apkFile": "/apk/game-sample.apk"
  },
  {
    "id": 18,
    "name": "Duolingo",
    "category": "Education",
    "price": null,
    "priceLabel": "Free",
    "description": "Learn languages through fun, bite-sized lessons and games.",
    "rating": 4.7,
    "reviews": 18000,
    "imageUrl": "https://cdn-icons-png.flaticon.com/512/5968/5968704.png",
    "isPaid": false,
    "features": [
      "35+ languages available",
      "Game-like learning experience",
      "Progress tracking",
      "Skill practice",
      "Daily goals and streaks",
      "Speaking exercises"
    ],
    "screenshots": [],
    "developer": "Duolingo",
    "releaseDate": "February 5, 2023",
    "version": "5.5.2",
    "size": "25 MB",
    "website": "https://example.com/duolingo",
    "apkFile": "/apk/sample-app.apk"
  },
  {
    "id": 19,
    "name": "HomeSecure",
    "category": "Tools",
    "price": "4.99",
    "priceLabel": "$4.99",
    "description": "Smart home security system controller with camera feeds, alerts, and automation.",
    "rating": 4.3,
    "reviews": 4200,
    "imageUrl": "https://cdn-icons-png.flaticon.com/512/2574/2574292.png",
    "isPaid": true,
    "features": [
      "Live camera feeds",
      "Motion detection alerts",
      "Door/window sensor monitoring",
      "Smart device integration",
      "Activity logs",
      "Emergency services contact"
    ],
    "screenshots": [],
    "developer": "Smart Home Systems",
    "releaseDate": "March 5, 2023",
    "version": "3.2.1",
    "size": "38 MB",
    "website": "https://example.com/homesecure",
    "apkFile": "/apk/game-sample.apk"
  },
  {
    "id": 20,
    "name": "PuzzleMaster",
    "category": "Games",
    "price": "0.99",
    "priceLabel": "$0.99",
    "description": "Collection of brain teasers, puzzles, and logic games for all ages.",
    "rating": 4.5,
    "reviews": 7200,
    "imageUrl": "https://cdn-icons-png.flaticon.com/512/3069/3069173.png",
    "isPaid": true,
    "features": [
      "500+ puzzles and brain teasers",
      "Multiple difficulty levels",
      "Daily puzzle challenges",
      "Progress tracking",
      "Hint system",
      "Offline play"
    ],
    "screenshots": [],
    "developer": "Mind Games Studio",
    "releaseDate": "April 18, 2023",
    "version": "2.7.0",
    "size": "65 MB",
    "website": "https://example.com/puzzlemaster",
    "apkFile": "/apk/sample-app.apk"
  },
  {
    "id": 21,
    "name": "CalendarPro",
    "category": "Productivity",
    "price": "1.99",
    "priceLabel": "$1.99",
    "description": "Advanced calendar app with scheduling, reminders, and integration with other services.",
    "rating": 4.6,
    "reviews": 5800,
    "imageUrl": "https://cdn-icons-png.flaticon.com/512/2693/2693507.png",
    "isPaid": true,
    "features": [
      "Multiple calendar views",
      "Smart event scheduling",
      "Task integration",
      "Custom reminders",
      "Weather forecast integration",
      "Calendar sharing"
    ],
    "screenshots": [],
    "developer": "ProductiveApps Inc.",
    "releaseDate": "January 25, 2023",
    "version": "3.4.5",
    "size": "32 MB",
    "website": "https://example.com/calendarpro",
    "apkFile": "/apk/game-sample.apk"
  },
  {
    "id": 22,
    "name": "Kindle",
    "category": "Books & Reference",
    "price": null,
    "priceLabel": "Free",
    "description": "E-reader app with millions of books, newspapers, and magazines.",
    "rating": 4.7,
    "reviews": 22000,
    "imageUrl": "https://cdn-icons-png.flaticon.com/512/5968/5968799.png",
    "isPaid": false,
    "features": [
      "Millions of books, magazines, and newspapers",
      "Adjustable reading settings",
      "Bookmarks and highlights",
      "Built-in dictionary",
      "Night reading mode",
      "Whispersync technology"
    ],
    "screenshots": [],
    "developer": "Amazon Mobile LLC",
    "releaseDate": "February 10, 2023",
    "version": "8.3.0",
    "size": "75 MB",
    "website": "https://example.com/kindle",
    "apkFile": "/apk/sample-app.apk"
  },
  {
    "id": 23,
    "name": "MusicMaker",
    "category": "Music & Audio",
    "price": "3.99",
    "priceLabel": "$3.99",
    "description": "Create music with virtual instruments, loops, and recording capabilities.",
    "rating": 4.4,
    "reviews": 4800,
    "imageUrl": "https://cdn-icons-png.flaticon.com/512/2995/2995101.png",
    "isPaid": true,
    "features": [
      "Multiple virtual instruments",
      "Beat and loop creation",
      "Audio recording",
      "Track mixing",
      "Audio effects",
      "Project export and sharing"
    ],
    "screenshots": [],
    "developer": "Creative Audio Labs",
    "releaseDate": "March 18, 2023",
    "version": "2.8.1",
    "size": "95 MB",
    "website": "https://example.com/musicmaker",
    "apkFile": "/apk/game-sample.apk"
  },
  {
    "id": 24,
    "name": "SketchArt",
    "category": "Art & Design",
    "price": "2.99",
    "priceLabel": "$2.99",
    "description": "Digital drawing and painting app with professional tools and brushes.",
    "rating": 4.6,
    "reviews": 6500,
    "imageUrl": "https://cdn-icons-png.flaticon.com/512/1048/1048944.png",
    "isPaid": true,
    "features": [
      "100+ brushes and tools",
      "Layer support",
      "Canvas sizes up to 4K",
      "PSD file compatibility",
      "Perspective guides",
      "Drawing timelapses"
    ],
    "screenshots": [],
    "developer": "Creative Design Studio",
    "releaseDate": "April 5, 2023",
    "version": "4.2.0",
    "size": "85 MB",
    "website": "https://example.com/sketchart",
    "apkFile": "/apk/sample-app.apk"
  },
  {
    "id": 25,
    "name": "NavGPS",
    "category": "Maps & Navigation",
    "price": null,
    "priceLabel": "Free",
    "description": "Turn-by-turn navigation with real-time traffic, alternate routes, and offline maps.",
    "rating": 4.5,
    "reviews": 14000,
    "imageUrl": "https://cdn-icons-png.flaticon.com/512/854/854878.png",
    "isPaid": false,
    "features": [
      "Turn-by-turn navigation",
      "Real-time traffic updates",
      "Offline maps",
      "Voice guidance",
      "Speed limit warnings",
      "Points of interest"
    ],
    "screenshots": [],
    "developer": "Navigation Technologies",
    "releaseDate": "February 15, 2023",
    "version": "5.1.2",
    "size": "62 MB",
    "website": "https://example.com/navgps",
    "apkFile": "/apk/game-sample.apk"
  },
  {
    "id": 26,
    "name": "DocuSign",
    "category": "Business",
    "price": null,
    "priceLabel": "Free",
    "description": "Electronic document signing and management platform.",
    "rating": 4.7,
    "reviews": 9200,
    "imageUrl": "https://cdn-icons-png.flaticon.com/512/6295/6295417.png",
    "isPaid": false,
    "features": [
      "Electronic signatures",
      "Document sending and receiving",
      "Template creation",
      "Signature tracking",
      "Secure document storage",
      "Multiple signer coordination"
    ],
    "screenshots": [],
    "developer": "DocuSign Inc.",
    "releaseDate": "January 30, 2023",
    "version": "3.8.5",
    "size": "45 MB",
    "website": "https://example.com/docusign",
    "apkFile": "/apk/sample-app.apk"
  },
  {
    "id": 27,
    "name": "DriveSafe",
    "category": "Travel & Local",
    "price": "2.49",
    "priceLabel": "$2.49",
    "description": "Driver safety app with speed monitoring, driving habits analysis, and crash detection.",
    "rating": 4.3,
    "reviews": 3500,
    "imageUrl": "https://cdn-icons-png.flaticon.com/512/3097/3097150.png",
    "isPaid": true,
    "features": [
      "Speed monitoring",
      "Driving habits analysis",
      "Crash detection",
      "Driver scoring",
      "Trip logging",
      "Emergency contacts"
    ],
    "screenshots": [],
    "developer": "Safe Driving Technologies",
    "releaseDate": "March 28, 2023",
    "version": "2.3.0",
    "size": "28 MB",
    "website": "https://example.com/drivesafe",
    "apkFile": "/apk/game-sample.apk"
  },
  {
    "id": 28,
    "name": "FilmFlix",
    "category": "Entertainment",
    "price": null,
    "priceLabel": "Free",
    "description": "Streaming service for movies and TV shows with personalized recommendations.",
    "rating": 4.8,
    "reviews": 18500,
    "imageUrl": "https://cdn-icons-png.flaticon.com/512/732/732228.png",
    "isPaid": false,
    "features": [
      "Thousands of movies and TV shows",
      "Personalized recommendations",
      "Multiple user profiles",
      "Download for offline viewing",
      "4K Ultra HD quality",
      "Watchlist creation"
    ],
    "screenshots": [],
    "developer": "FilmFlix Entertainment",
    "releaseDate": "January 5, 2023",
    "version": "7.2.1",
    "size": "32 MB",
    "website": "https://example.com/filmflix",
    "apkFile": "/apk/sample-app.apk"
  },
  {
    "id": 29,
    "name": "CodeLearn",
    "category": "Education",
    "price": "5.99",
    "priceLabel": "$5.99",
    "description": "Learn programming languages with interactive courses, coding exercises, and projects.",
    "rating": 4.6,
    "reviews": 7800,
    "imageUrl": "https://cdn-icons-png.flaticon.com/512/1005/1005141.png",
    "isPaid": true,
    "features": [
      "15+ programming languages",
      "Interactive coding exercises",
      "Project-based learning",
      "Code challenges",
      "Community forum",
      "Certificate of completion"
    ],
    "screenshots": [],
    "developer": "Education Technology Labs",
    "releaseDate": "February 22, 2023",
    "version": "3.5.2",
    "size": "65 MB",
    "website": "https://example.com/codelearn",
    "apkFile": "/apk/game-sample.apk"
  },
  {
    "id": 30,
    "name": "PetPal",
    "category": "Lifestyle",
    "price": "1.99",
    "priceLabel": "$1.99",
    "description": "Pet care tracking and management app for schedules, health records, and reminders.",
    "rating": 4.5,
    "reviews": 4200,
    "imageUrl": "https://cdn-icons-png.flaticon.com/512/616/616408.png",
    "isPaid": true,
    "features": [
      "Pet health record tracking",
      "Medication and vaccination reminders",
      "Feeding and exercise schedules",
      "Vet appointment management",
      "Pet photo journal",
      "Pet care tips"
    ],
    "screenshots": [],
    "developer": "Pet Technology Solutions",
    "releaseDate": "April 10, 2023",
    "version": "2.1.4",
    "size": "35 MB",
    "website": "https://example.com/petpal",
    "apkFile": "/apk/sample-app.apk"
  },
  {
    "id": 31,
    "name": "QuickScan",
    "category": "Tools",
    "price": null,
    "priceLabel": "Free",
    "description": "QR code and barcode scanner with history and generation capabilities.",
    "rating": 4.4,
    "reviews": 9500,
    "imageUrl": "https://cdn-icons-png.flaticon.com/512/1073/1073726.png",
    "isPaid": false,
    "features": [
      "Fast QR and barcode scanning",
      "Scan history",
      "QR code generation",
      "Direct link opening",
      "Batch scanning mode",
      "Flashlight support"
    ],
    "screenshots": [],
    "developer": "Quick Tools",
    "releaseDate": "March 8, 2023",
    "version": "2.5.0",
    "size": "15 MB",
    "website": "https://example.com/quickscan",
    "apkFile": "/apk/game-sample.apk"
  },
  {
    "id": 32,
    "name": "WordMaster",
    "category": "Games",
    "price": "0.99",
    "priceLabel": "$0.99",
    "description": "Word puzzle game to enhance vocabulary and spelling skills.",
    "rating": 4.6,
    "reviews": 8300,
    "imageUrl": "https://cdn-icons-png.flaticon.com/512/1205/1205526.png",
    "isPaid": true,
    "features": [
      "1000+ word puzzles",
      "Daily challenges",
      "Multiple difficulty levels",
      "Vocabulary builder",
      "Offline play",
      "Leaderboards"
    ],
    "screenshots": [],
    "developer": "Word Game Studios",
    "releaseDate": "January 18, 2023",
    "version": "3.2.1",
    "size": "45 MB",
    "website": "https://example.com/wordmaster",
    "apkFile": "/apk/sample-app.apk"
  },
  {
    "id": 33,
    "name": "StockTracker",
    "category": "Finance",
    "price": "4.99",
    "priceLabel": "$4.99",
    "description": "Investment and stock market tracking app with real-time data and portfolio management.",
    "rating": 4.7,
    "reviews": 6500,
    "imageUrl": "https://cdn-icons-png.flaticon.com/512/2271/2271985.png",
    "isPaid": true,
    "features": [
      "Real-time stock market data",
      "Portfolio tracking",
      "Investment insights",
      "Price alerts",
      "News integration",
      "Interactive charts"
    ],
    "screenshots": [],
    "developer": "Financial Data Systems",
    "releaseDate": "February 25, 2023",
    "version": "5.0.2",
    "size": "38 MB",
    "website": "https://example.com/stocktracker",
    "apkFile": "/apk/game-sample.apk"
  },
  {
    "id": 34,
    "name": "VoiceRecorder",
    "category": "Tools",
    "price": null,
    "priceLabel": "Free",
    "description": "High-quality audio recorder with editing, transcription, and organization features.",
    "rating": 4.5,
    "reviews": 7200,
    "imageUrl": "https://cdn-icons-png.flaticon.com/512/25/25694.png",
    "isPaid": false,
    "features": [
      "High-quality audio recording",
      "Recording editing",
      "Speech-to-text transcription",
      "Recording organization",
      "Cloud backup",
      "Recording sharing"
    ],
    "screenshots": [],
    "developer": "Audio Tools Inc.",
    "releaseDate": "March 15, 2023",
    "version": "2.7.3",
    "size": "25 MB",
    "website": "https://example.com/voicerecorder",
    "apkFile": "/apk/sample-app.apk"
  },
  {
    "id": 35,
    "name": "FitnessCoach",
    "category": "Health & Fitness",
    "price": "3.49",
    "priceLabel": "$3.49",
    "description": "Virtual personal trainer with workout plans, exercise guides, and progress tracking.",
    "rating": 4.8,
    "reviews": 9800,
    "imageUrl": "https://cdn-icons-png.flaticon.com/512/2964/2964514.png",
    "isPaid": true,
    "features": [
      "Personalized workout plans",
      "Video exercise guides",
      "Fitness goal setting",
      "Progress tracking",
      "Nutritional advice",
      "Workout reminders"
    ],
    "screenshots": [],
    "developer": "Fitness Technology Corp",
    "releaseDate": "April 5, 2023",
    "version": "4.1.0",
    "size": "75 MB",
    "website": "https://example.com/fitnesscoach",
    "apkFile": "/apk/game-sample.apk"
  },
  {
    "id": 36,
    "name": "EmailPro",
    "category": "Productivity",
    "price": "2.99",
    "priceLabel": "$2.99",
    "description": "Advanced email client with organization features, smart filters, and multi-account support.",
    "rating": 4.4,
    "reviews": 5600,
    "imageUrl": "https://cdn-icons-png.flaticon.com/512/561/561127.png",
    "isPaid": true,
    "features": [
      "Multiple email account support",
      "Smart inbox organization",
      "Email scheduling",
      "Snooze function",
      "Custom swipe actions",
      "Integrated calendar"
    ],
    "screenshots": [],
    "developer": "Productivity Software Inc.",
    "releaseDate": "January 12, 2023",
    "version": "3.8.2",
    "size": "42 MB",
    "website": "https://example.com/emailpro",
    "apkFile": "/apk/sample-app.apk"
  },
  {
    "id": 37,
    "name": "CryptoTracker",
    "category": "Finance",
    "price": null,
    "priceLabel": "Free",
    "description": "Cryptocurrency tracking and portfolio management with real-time market data.",
    "rating": 4.5,
    "reviews": 8200,
    "imageUrl": "https://cdn-icons-png.flaticon.com/512/1092/1092712.png",
    "isPaid": false,
    "features": [
      "Real-time cryptocurrency prices",
      "Portfolio tracking",
      "Price alerts",
      "Historical data charts",
      "News feed",
      "Market trends analysis"
    ],
    "screenshots": [],
    "developer": "Crypto Technologies",
    "releaseDate": "February 5, 2023",
    "version": "3.2.0",
    "size": "30 MB",
    "website": "https://example.com/cryptotracker",
    "apkFile": "/apk/game-sample.apk"
  },
  {
    "id": 38,
    "name": "TicTacToe Pro",
    "category": "Games",
    "price": "0.49",
    "priceLabel": "$0.49",
    "description": "Classic tic-tac-toe game with multiple difficulty levels and online multiplayer.",
    "rating": 4.3,
    "reviews": 4500,
    "imageUrl": "https://cdn-icons-png.flaticon.com/512/566/566294.png",
    "isPaid": true,
    "features": [
      "Single player vs AI",
      "Online multiplayer",
      "Multiple difficulty levels",
      "Custom game boards",
      "Statistics tracking",
      "Achievement system"
    ],
    "screenshots": [],
    "developer": "Classic Games Studio",
    "releaseDate": "March 22, 2023",
    "version": "2.0.1",
    "size": "18 MB",
    "website": "https://example.com/tictactoepro",
    "apkFile": "/apk/sample-app.apk"
  },
  {
    "id": 39,
    "name": "PDFViewer",
    "category": "Productivity",
    "price": null,
    "priceLabel": "Free",
    "description": "PDF reader with annotation, form filling, and document management features.",
    "rating": 4.6,
    "reviews": 12000,
    "imageUrl": "https://cdn-icons-png.flaticon.com/512/337/337946.png",
    "isPaid": false,
    "features": [
      "PDF viewing and navigation",
      "Annotation and highlighting",
      "Form filling and signing",
      "Document organization",
      "Cloud storage integration",
      "PDF conversion"
    ],
    "screenshots": [],
    "developer": "Document Solutions",
    "releaseDate": "January 28, 2023",
    "version": "4.5.0",
    "size": "35 MB",
    "website": "https://example.com/pdfviewer",
    "apkFile": "/apk/game-sample.apk"
  },
  {
    "id": 40,
    "name": "MeditationZen",
    "category": "Health & Fitness",
    "price": "1.99",
    "priceLabel": "$1.99",
    "description": "Guided meditation and mindfulness practices for stress reduction and better sleep.",
    "rating": 4.7,
    "reviews": 8800,
    "imageUrl": "https://cdn-icons-png.flaticon.com/512/2647/2647625.png",
    "isPaid": true,
    "features": [
      "Guided meditation sessions",
      "Sleep stories",
      "Breathing exercises",
      "Relaxing sounds and music",
      "Meditation timer",
      "Progress tracking"
    ],
    "screenshots": [],
    "developer": "Zen Mindfulness LLC",
    "releaseDate": "February 18, 2023",
    "version": "3.4.1",
    "size": "55 MB",
    "website": "https://example.com/meditationzen",
    "apkFile": "/apk/sample-app.apk"
  },
  {
    "id": 41,
    "name": "CameraPlus",
    "category": "Photography",
    "price": "2.49",
    "priceLabel": "$2.49",
    "description": "Advanced camera app with professional controls, filters, and editing tools.",
    "rating": 4.5,
    "reviews": 7500,
    "imageUrl": "https://cdn-icons-png.flaticon.com/512/3178/3178174.png",
    "isPaid": true,
    "features": [
      "Manual camera controls",
      "RAW image capture",
      "Real-time filters",
      "Photo editing tools",
      "Timer and burst modes",
      "Custom presets"
    ],
    "screenshots": [],
    "developer": "Pro Photography Apps",
    "releaseDate": "March 12, 2023",
    "version": "4.2.0",
    "size": "65 MB",
    "website": "https://example.com/cameraplus",
    "apkFile": "/apk/game-sample.apk"
  },
  {
    "id": 42,
    "name": "SuperVPN",
    "category": "Tools",
    "price": "3.99",
    "priceLabel": "$3.99",
    "description": "Secure VPN service for private browsing, data protection, and access to geo-restricted content.",
    "rating": 4.4,
    "reviews": 15000,
    "imageUrl": "https://cdn-icons-png.flaticon.com/512/6711/6711205.png",
    "isPaid": true,
    "features": [
      "Secure encryption",
      "Multiple server locations",
      "No-logs policy",
      "Unlimited bandwidth",
      "Kill switch feature",
      "Fast connection speeds"
    ],
    "screenshots": [],
    "developer": "Security Solutions Inc.",
    "releaseDate": "January 15, 2023",
    "version": "5.0.2",
    "size": "28 MB",
    "website": "https://example.com/supervpn",
    "apkFile": "/apk/sample-app.apk"
  },
  {
    "id": 43,
    "name": "DrumBeats",
    "category": "Music & Audio",
    "price": null,
    "priceLabel": "Free",
    "description": "Virtual drum kit with realistic sounds, beat patterns, and recording capabilities.",
    "rating": 4.2,
    "reviews": 6200,
    "imageUrl": "https://cdn-icons-png.flaticon.com/512/3659/3659784.png",
    "isPaid": false,
    "features": [
      "Realistic drum sounds",
      "Multiple drum kits",
      "Beat patterns and loops",
      "Recording function",
      "Metronome",
      "Audio export"
    ],
    "screenshots": [],
    "developer": "Audio App Labs",
    "releaseDate": "March 25, 2023",
    "version": "2.3.5",
    "size": "48 MB",
    "website": "https://example.com/drumbeats",
    "apkFile": "/apk/game-sample.apk"
  },
  {
    "id": 44,
    "name": "PasswordVault",
    "category": "Tools",
    "price": "4.99",
    "priceLabel": "$4.99",
    "description": "Secure password manager with auto-fill, generator, and breach monitoring.",
    "rating": 4.8,
    "reviews": 9600,
    "imageUrl": "https://cdn-icons-png.flaticon.com/512/3064/3064197.png",
    "isPaid": true,
    "features": [
      "Secure password storage",
      "Password generator",
      "Auto-fill capability",
      "Breach monitoring",
      "Cross-device syncing",
      "Secure notes"
    ],
    "screenshots": [],
    "developer": "Security Tech Solutions",
    "releaseDate": "February 8, 2023",
    "version": "4.2.1",
    "size": "32 MB",
    "website": "https://example.com/passwordvault",
    "apkFile": "/apk/sample-app.apk"
  },
  {
    "id": 45,
    "name": "SpeechTranslator",
    "category": "Tools",
    "price": "1.99",
    "priceLabel": "$1.99",
    "description": "Real-time speech and text translation for multiple languages.",
    "rating": 4.5,
    "reviews": 7800,
    "imageUrl": "https://cdn-icons-png.flaticon.com/512/3898/3898840.png",
    "isPaid": true,
    "features": [
      "Support for 50+ languages",
      "Real-time speech translation",
      "Text translation",
      "Offline mode for selected languages",
      "Conversation mode",
      "Pronunciation guides"
    ],
    "screenshots": [],
    "developer": "Translation Technologies",
    "releaseDate": "April 2, 2023",
    "version": "3.5.0",
    "size": "45 MB",
    "website": "https://example.com/speechtranslator",
    "apkFile": "/apk/game-sample.apk"
  },
  {
    "id": 46,
    "name": "RecipeFinder",
    "category": "Food & Drink",
    "price": null,
    "priceLabel": "Free",
    "description": "Find recipes based on ingredients you have, dietary preferences, and cooking time.",
    "rating": 4.6,
    "reviews": 8500,
    "imageUrl": "https://cdn-icons-png.flaticon.com/512/1830/1830839.png",
    "isPaid": false,
    "features": [
      "Search by ingredients",
      "Dietary filters",
      "Recipe saving",
      "Step-by-step instructions",
      "Nutritional information",
      "Weekly meal planning"
    ],
    "screenshots": [],
    "developer": "Food Tech Solutions",
    "releaseDate": "March 10, 2023",
    "version": "2.7.3",
    "size": "38 MB",
    "website": "https://example.com/recipefinder",
    "apkFile": "/apk/sample-app.apk"
  },
  {
    "id": 47,
    "name": "ChatMaster",
    "category": "Communication",
    "price": null,
    "priceLabel": "Free",
    "description": "Messaging app with group chats, video calls, and file sharing capabilities.",
    "rating": 4.7,
    "reviews": 18000,
    "imageUrl": "https://cdn-icons-png.flaticon.com/512/724/724715.png",
    "isPaid": false,
    "features": [
      "One-on-one messaging",
      "Group chats",
      "Video and audio calls",
      "File and media sharing",
      "End-to-end encryption",
      "Message editing and deletion"
    ],
    "screenshots": [],
    "developer": "Communication Apps Inc.",
    "releaseDate": "January 20, 2023",
    "version": "5.2.0",
    "size": "42 MB",
    "website": "https://example.com/chatmaster",
    "apkFile": "/apk/game-sample.apk"
  },
  {
    "id": 48,
    "name": "ParkFinder",
    "category": "Travel & Local",
    "price": "0.99",
    "priceLabel": "$0.99",
    "description": "Find and pay for parking spots in real-time, with navigation and reminders.",
    "rating": 4.3,
    "reviews": 4200,
    "imageUrl": "https://cdn-icons-png.flaticon.com/512/708/708949.png",
    "isPaid": true,
    "features": [
      "Real-time parking availability",
      "Navigation to parking spots",
      "Mobile payment",
      "Parking timer and reminders",
      "Favorite parking locations",
      "Parking history"
    ],
    "screenshots": [],
    "developer": "Urban Mobility Solutions",
    "releaseDate": "February 28, 2023",
    "version": "2.1.5",
    "size": "35 MB",
    "website": "https://example.com/parkfinder",
    "apkFile": "/apk/sample-app.apk"
  },
  {
    "id": 49,
    "name": "AudioBooks",
    "category": "Books & Reference",
    "price": "4.99",
    "priceLabel": "$4.99",
    "description": "Audiobook player with thousands of titles, bookmarking, and sleep timer.",
    "rating": 4.6,
    "reviews": 9200,
    "imageUrl": "https://cdn-icons-png.flaticon.com/512/2232/2232688.png",
    "isPaid": true,
    "features": [
      "Large audiobook library",
      "Variable playback speed",
      "Bookmarking and notes",
      "Sleep timer",
      "Chapter navigation",
      "Offline listening"
    ],
    "screenshots": [],
    "developer": "Digital Books Inc.",
    "releaseDate": "March 5, 2023",
    "version": "3.8.0",
    "size": "52 MB",
    "website": "https://example.com/audiobooks",
    "apkFile": "/apk/game-sample.apk"
  },
  {
    "id": 50,
    "name": "StarGazer",
    "category": "Education",
    "price": "2.99",
    "priceLabel": "$2.99",
    "description": "Interactive astronomy guide with star maps, planet tracking, and space information.",
    "rating": 4.8,
    "reviews": 7500,
    "imageUrl": "https://cdn-icons-png.flaticon.com/512/3049/3049432.png",
    "isPaid": true,
    "features": [
      "Interactive star maps",
      "Planet and constellation tracking",
      "Space mission updates",
      "Astronomical event calendar",
      "Night mode for stargazing",
      "Educational content about space"
    ],
    "screenshots": [],
    "developer": "Space Education Labs",
    "releaseDate": "April 15, 2023",
    "version": "2.5.0",
    "size": "85 MB",
    "website": "https://example.com/stargazer",
    "apkFile": "/apk/sample-app.apk"
  }
]